trame/__init__.py
trame/modules/__init__.py
trame/modules/paraview.py
trame/modules/vtk.py
trame/tools/__init__.py
trame/tools/vtksz2html.py
trame/widgets/__init__.py
trame/widgets/paraview.py
trame/widgets/vtk.py
trame_vtk/__init__.py
trame_vtk/modules/__init__.py
trame_vtk/modules/common/__init__.py
trame_vtk/modules/common/serve/trame-vtk.js
trame_vtk/modules/paraview/__init__.py
trame_vtk/modules/paraview/core.py
trame_vtk/modules/paraview/protocols/__init__.py
trame_vtk/modules/paraview/protocols/local_rendering.py
trame_vtk/modules/paraview/protocols/mouse_handler.py
trame_vtk/modules/paraview/protocols/publish_image_delivery.py
trame_vtk/modules/paraview/protocols/view_port.py
trame_vtk/modules/paraview/protocols/web_protocol.py
trame_vtk/modules/vtk/__init__.py
trame_vtk/modules/vtk/core.py
trame_vtk/modules/vtk/widget.py
trame_vtk/modules/vtk/protocols/__init__.py
trame_vtk/modules/vtk/protocols/local_rendering.py
trame_vtk/modules/vtk/protocols/mouse_handler.py
trame_vtk/modules/vtk/protocols/publish_image_delivery.py
trame_vtk/modules/vtk/protocols/view_port.py
trame_vtk/modules/vtk/protocols/web_protocol.py
trame_vtk/modules/vtk/serializers/__init__.py
trame_vtk/modules/vtk/serializers/actors.py
trame_vtk/modules/vtk/serializers/cache.py
trame_vtk/modules/vtk/serializers/data.py
trame_vtk/modules/vtk/serializers/export.py
trame_vtk/modules/vtk/serializers/helpers.py
trame_vtk/modules/vtk/serializers/initialize.py
trame_vtk/modules/vtk/serializers/lights.py
trame_vtk/modules/vtk/serializers/lookup_tables.py
trame_vtk/modules/vtk/serializers/mappers.py
trame_vtk/modules/vtk/serializers/mesh.py
trame_vtk/modules/vtk/serializers/properties.py
trame_vtk/modules/vtk/serializers/registry.py
trame_vtk/modules/vtk/serializers/render_windows.py
trame_vtk/modules/vtk/serializers/serialize.py
trame_vtk/modules/vtk/serializers/synchronization_context.py
trame_vtk/modules/vtk/serializers/textures.py
trame_vtk/modules/vtk/serializers/utils.py
trame_vtk-2.10.1.dist-info/METADATA
trame_vtk-2.10.1.dist-info/WHEEL
trame_vtk-2.10.1.dist-info/licenses/LICENSE
trame_vtk-2.10.1.dist-info/RECORD
